common/logger.py
extractor/__init__.py
hydraedge/__init__.py
hydraedge-0.1.1.dist-info/licenses/LICENSE
model/cosine_kernel.py
model/kernel_base.py
serve/app.py
training/runner.py
hydraedge-0.1.1.dist-info/METADATA
hydraedge-0.1.1.dist-info/WHEEL
hydraedge-0.1.1.dist-info/top_level.txt
hydraedge-0.1.1.dist-info/RECORD
