Metadata-Version: 2.4
Name: hydraedge
Version: 0.1.1
Summary: HydraEdge: cross-document linker (VSA × RL) – EMNLP 2025 system demo
Author-email: Pak Kin Lau <pakkin.lau@link.cuhk.edu.hk>, Stuart Michael McManus <smcmanus@cuhk.edu.hk>
License: Copyright 2025 Pak Kin LAU
Project-URL: Homepage, https://github.com/pakkinlau/hydraedge
Project-URL: Repository, https://github.com/pakkinlau/hydraedge.git
Keywords: hydra,cross-document,linking,VSA,reinforcement-learning
Classifier: Programming Language :: Python :: 3.10
Classifier: License :: OSI Approved :: MIT License
Classifier: Operating System :: OS Independent
License-File: LICENSE
Requires-Dist: fastapi>=0.110
Requires-Dist: uvicorn[standard]>=0.29
Requires-Dist: pydantic>=2.7
Requires-Dist: torch>=2.2
Requires-Dist: numpy>=1.26
Requires-Dist: pytest>=8.2
Requires-Dist: structlog>=24.1
Dynamic: license-file
